{"frameRate":30,"armature":[{"animation":[{"ffd":[{"frame":[{"offset":0,"tweenEasing":null,"vertices":[],"duration":10},{"offset":0,"tweenEasing":null,"vertices":[],"duration":20}],"skin":"","scale":1,"slot":"Layer 289","offset":0,"name":"Layer 289"}],"frame":[],"duration":30,"slot":[{"frame":[{"displayIndex":-1,"tweenEasing":0,"duration":11},{"tweenEasing":0,"duration":2},{"displayIndex":-1,"tweenEasing":0,"duration":17},{"displayIndex":-1,"tweenEasing":null,"duration":0}],"name":"282flip"},{"frame":[{"tweenEasing":0,"duration":11},{"displayIndex":-1,"tweenEasing":0,"duration":2},{"tweenEasing":0,"duration":17},{"tweenEasing":null,"duration":0}],"name":"Layer 285"},{"frame":[{"displayIndex":-1,"tweenEasing":0,"duration":11},{"tweenEasing":0,"duration":6},{"tweenEasing":null,"color":{"aM":0},"duration":13}],"name":"smear"}],"ik":[],"bone":[{"frame":[{"transform":{},"duration":10},{"transform":{},"duration":20},{"transform":{},"duration":0}],"name":"root"},{"frame":[{"curve":[0.25,0,1,0],"transform":{},"duration":10},{"curve":[0.25,0,0,1],"transform":{"y":-8.91,"x":39.2},"duration":5},{"tweenEasing":0,"transform":{"y":46.77,"x":-19.09},"duration":15},{"transform":{},"duration":0}],"name":"mid"},{"frame":[{"transform":{},"duration":10},{"curve":[0.25,0,0,1],"transform":{},"duration":5},{"tweenEasing":0,"transform":{"skX":-11.15,"skY":-11.15},"duration":15},{"transform":{},"duration":0}],"name":"bone2"},{"frame":[{"transform":{},"duration":10},{"curve":[0.25,0,0,1],"transform":{},"duration":5},{"tweenEasing":0,"transform":{"skX":-15.62,"skY":-15.62},"duration":15},{"transform":{},"duration":0}],"name":"bone3"},{"frame":[{"curve":[0.25,0,1,0],"transform":{},"duration":10},{"curve":[0.25,0,0,1],"transform":{"skX":13.77,"skY":13.77},"duration":5},{"tweenEasing":0,"transform":{"skX":3.93,"skY":3.93},"duration":15},{"transform":{},"duration":0}],"name":"bone4"},{"frame":[{"transform":{},"duration":10},{"transform":{},"duration":5},{"transform":{},"duration":15},{"transform":{},"duration":0}],"name":"bone5"},{"frame":[{"curve":[0.25,0,1,0],"transform":{},"duration":10},{"curve":[0.25,0,0,1],"transform":{"skX":-68.85,"skY":-68.85},"duration":1},{"curve":[0.25,0,0.75,1],"transform":{"skX":-202.22,"skY":-202.22},"duration":4},{"tweenEasing":0,"transform":{"skX":6.38,"skY":6.38},"duration":15},{"transform":{},"duration":0}],"name":"bone6"},{"frame":[{"transform":{},"duration":10},{"curve":[0.25,0,0,1],"transform":{},"duration":5},{"tweenEasing":0,"transform":{"skX":45.84,"skY":45.84},"duration":15},{"transform":{},"duration":0}],"name":"bone7"},{"frame":[{"curve":[0.25,0,1,0],"transform":{},"duration":10},{"curve":[0.25,0,0,1],"transform":{"skX":69.39,"skY":69.39},"duration":1},{"curve":[0.25,0,0.75,1],"transform":{"y":84.08,"x":-45.66,"skX":209.65,"skY":209.65},"duration":4},{"tweenEasing":0,"transform":{"y":18.12,"x":-1.93,"skX":171.69,"skY":171.69},"duration":15},{"transform":{},"duration":0}],"name":"bone8"},{"frame":[{"curve":[0.25,0,1,0],"transform":{},"duration":10},{"curve":[0.25,0,0,1],"transform":{"skX":-3.05,"skY":-3.05},"duration":5},{"tweenEasing":0,"transform":{"skX":-2.6,"skY":-2.6},"duration":15},{"transform":{},"duration":0}],"name":"bone9"},{"frame":[{"curve":[0.25,0,1,0],"transform":{},"duration":10},{"transform":{"skX":-3.58,"skY":-3.58},"duration":5},{"tweenEasing":0,"transform":{"skX":-3.58,"skY":-3.58},"duration":15},{"transform":{},"duration":0}],"name":"bone10"},{"frame":[{"curve":[0.25,0,1,0],"transform":{},"duration":10},{"curve":[0.25,0,0,1],"transform":{"skX":-39.66,"skY":-39.66},"duration":5},{"tweenEasing":0,"transform":{"skX":-5.97,"skY":-5.97},"duration":15},{"transform":{},"duration":0}],"name":"bone11"},{"frame":[{"transform":{},"duration":10},{"transform":{},"duration":5},{"transform":{},"duration":15},{"transform":{},"duration":0}],"name":"mid2"},{"frame":[{"transform":{},"duration":10},{"transform":{},"duration":5},{"transform":{},"duration":15},{"transform":{},"duration":0}],"name":"mid3"},{"frame":[{"transform":{},"duration":10},{"transform":{},"duration":5},{"transform":{},"duration":15},{"transform":{},"duration":0}],"name":"mid4"},{"frame":[{"curve":[0.25,0,1,0],"transform":{},"duration":10},{"transform":{"skX":18.42,"skY":18.42},"duration":5},{"tweenEasing":0,"transform":{"skX":18.42,"skY":18.42},"duration":15},{"transform":{},"duration":0}],"name":"bone12"},{"frame":[{"transform":{},"duration":10},{"curve":[0.25,0,0,1],"transform":{},"duration":5},{"tweenEasing":0,"transform":{"skX":10.39,"skY":10.39},"duration":15},{"transform":{},"duration":0}],"name":"mid5"},{"frame":[{"curve":[0.25,0,1,0],"transform":{},"duration":10},{"curve":[0.25,0,0,1],"transform":{"skX":-51.5,"skY":-51.5},"duration":5},{"tweenEasing":0,"transform":{"skX":-27.79,"skY":-27.79},"duration":15},{"transform":{},"duration":0}],"name":"bone13"},{"frame":[{"transform":{},"duration":10},{"curve":[0.25,0,0,1],"transform":{},"duration":5},{"tweenEasing":0,"transform":{"skX":-19.33,"skY":-19.33},"duration":15},{"transform":{},"duration":0}],"name":"bone14"},{"frame":[{"transform":{},"duration":10},{"transform":{},"duration":5},{"transform":{},"duration":15},{"transform":{},"duration":0}],"name":"bone15"},{"frame":[{"curve":[0.25,0,1,0],"transform":{},"duration":10},{"transform":{"scX":0.82},"duration":5},{"tweenEasing":0,"transform":{"scX":0.82},"duration":15},{"transform":{},"duration":0}],"name":"bone"},{"frame":[{"transform":{},"duration":10},{"transform":{},"duration":5},{"transform":{},"duration":15},{"transform":{},"duration":0}],"name":"bone16"},{"frame":[{"tweenEasing":0,"transform":{},"duration":10},{"transform":{},"duration":20}],"name":"bone19"},{"frame":[{"tweenEasing":0,"transform":{},"duration":10},{"curve":[0.25,0,0,1],"transform":{},"duration":1},{"curve":[0.25,0,0.75,1],"transform":{"skX":-217.09,"skY":-217.09},"duration":1},{"curve":[0.25,0,0.75,1],"transform":{"skX":-267.79,"skY":-267.79},"duration":3},{"tweenEasing":0,"transform":{"skX":-37.45,"skY":-37.45},"duration":15},{"transform":{"skX":-30.78,"skY":-30.78},"duration":0}],"name":"bone17"},{"frame":[{"tweenEasing":0,"transform":{},"duration":10},{"transform":{},"duration":5},{"transform":{},"duration":15}],"name":"bone18"},{"frame":[{"tweenEasing":0,"transform":{},"duration":10},{"tweenEasing":0,"transform":{},"duration":4},{"transform":{},"duration":16}],"name":"bone20"},{"frame":[{"tweenEasing":0,"transform":{},"duration":11},{"transform":{"y":313.12,"x":168.01,"skX":-54.25,"skY":-54.25},"duration":19}],"name":"FX"}],"name":"Attack A"},{"ffd":[{"frame":[{"offset":0,"tweenEasing":null,"vertices":[],"duration":10},{"offset":0,"tweenEasing":null,"vertices":[],"duration":5},{"offset":0,"tweenEasing":null,"vertices":[],"duration":20}],"skin":"","scale":1,"slot":"Layer 289","offset":0,"name":"Layer 289"}],"frame":[],"duration":35,"slot":[{"frame":[{"displayIndex":-1,"tweenEasing":0,"duration":16},{"tweenEasing":0,"duration":2},{"displayIndex":-1,"tweenEasing":0,"duration":17},{"displayIndex":-1,"tweenEasing":null,"duration":0}],"name":"282flip"},{"frame":[{"tweenEasing":0,"duration":16},{"displayIndex":-1,"tweenEasing":0,"duration":2},{"tweenEasing":0,"duration":17},{"tweenEasing":null,"duration":0}],"name":"Layer 285"},{"frame":[{"displayIndex":-1,"tweenEasing":0,"duration":16},{"tweenEasing":0,"duration":7},{"tweenEasing":null,"color":{"aM":0},"duration":12}],"name":"smear"}],"ik":[],"bone":[{"frame":[{"transform":{},"duration":10},{"transform":{},"duration":5},{"transform":{},"duration":20},{"transform":{},"duration":0}],"name":"root"},{"frame":[{"curve":[0.25,0,1,0],"transform":{},"duration":10},{"transform":{"y":-8.91,"x":39.2},"duration":5},{"curve":[0.25,0,0,1],"transform":{"y":-8.91,"x":39.2},"duration":5},{"transform":{"y":46.77,"x":-19.09},"duration":1},{"curve":[0.25,0,0.75,1],"transform":{"y":46.77,"x":-19.09},"duration":14},{"transform":{},"duration":0}],"name":"mid"},{"frame":[{"transform":{},"duration":10},{"transform":{},"duration":5},{"curve":[0.25,0,0,1],"transform":{},"duration":5},{"transform":{"skX":-11.15,"skY":-11.15},"duration":1},{"curve":[0.25,0,0.75,1],"transform":{"skX":-11.15,"skY":-11.15},"duration":14},{"transform":{},"duration":0}],"name":"bone2"},{"frame":[{"transform":{},"duration":10},{"transform":{},"duration":5},{"curve":[0.25,0,0,1],"transform":{},"duration":5},{"transform":{"skX":-15.62,"skY":-15.62},"duration":1},{"curve":[0.25,0,0.75,1],"transform":{"skX":-15.62,"skY":-15.62},"duration":14},{"transform":{},"duration":0}],"name":"bone3"},{"frame":[{"curve":[0.25,0,1,0],"transform":{},"duration":10},{"transform":{"skX":13.77,"skY":13.77},"duration":5},{"curve":[0.25,0,0,1],"transform":{"skX":13.77,"skY":13.77},"duration":5},{"transform":{"skX":3.93,"skY":3.93},"duration":1},{"curve":[0.25,0,0.75,1],"transform":{"skX":3.93,"skY":3.93},"duration":14},{"transform":{},"duration":0}],"name":"bone4"},{"frame":[{"transform":{},"duration":10},{"transform":{},"duration":5},{"transform":{},"duration":5},{"transform":{},"duration":1},{"transform":{},"duration":14},{"transform":{},"duration":0}],"name":"bone5"},{"frame":[{"curve":[0.25,0,1,0],"transform":{},"duration":10},{"curve":[0.481,0,0.769,0.38],"transform":{"skX":-68.85,"skY":-68.85},"duration":1},{"curve":[0.353,0.26,0.618,0.61],"transform":{"y":8.74,"x":4.15,"skX":-68.85,"skY":-68.85},"duration":1},{"curve":[0.224,0.32,0.517,0.68],"transform":{"y":7.03,"x":-7.37,"skX":-68.85,"skY":-68.85},"duration":1},{"curve":[0.226,0.39,0.54,0.74],"transform":{"y":-1.75,"x":5.61,"skX":-68.85,"skY":-68.85},"duration":1},{"curve":[0.246,0.62,0.569,1],"transform":{"y":-7.15,"x":-2.36,"skX":-68.85,"skY":-68.85},"duration":1},{"curve":[0.25,0,0,1],"transform":{"skX":-68.85,"skY":-68.85},"duration":1},{"curve":[0.25,0,0.75,1],"transform":{"skX":-202.22,"skY":-202.22},"duration":4},{"transform":{"skX":6.38,"skY":6.38},"duration":1},{"curve":[0.25,0,0.75,1],"transform":{"skX":6.38,"skY":6.38},"duration":14},{"transform":{},"duration":0}],"name":"bone6"},{"frame":[{"transform":{},"duration":10},{"transform":{},"duration":5},{"curve":[0.25,0,0,1],"transform":{},"duration":5},{"transform":{"skX":45.84,"skY":45.84},"duration":1},{"curve":[0.25,0,0.75,1],"transform":{"skX":45.84,"skY":45.84},"duration":14},{"transform":{},"duration":0}],"name":"bone7"},{"frame":[{"curve":[0.25,0,1,0],"transform":{},"duration":10},{"transform":{"skX":69.39,"skY":69.39},"duration":5},{"curve":[0.25,0,0,1],"transform":{"skX":69.39,"skY":69.39},"duration":1},{"curve":[0.25,0,0.75,1],"transform":{"y":84.08,"x":-45.66,"skX":209.65,"skY":209.65},"duration":4},{"transform":{"y":18.12,"x":-1.93,"skX":171.69,"skY":171.69},"duration":1},{"curve":[0.25,0,0.75,1],"transform":{"y":18.12,"x":-1.93,"skX":171.69,"skY":171.69},"duration":14},{"transform":{},"duration":0}],"name":"bone8"},{"frame":[{"curve":[0.25,0,1,0],"transform":{},"duration":10},{"transform":{"skX":-3.05,"skY":-3.05},"duration":5},{"curve":[0.25,0,0,1],"transform":{"skX":-3.05,"skY":-3.05},"duration":5},{"transform":{"skX":-2.6,"skY":-2.6},"duration":1},{"curve":[0.25,0,0.75,1],"transform":{"skX":-2.6,"skY":-2.6},"duration":14},{"transform":{},"duration":0}],"name":"bone9"},{"frame":[{"curve":[0.25,0,1,0],"transform":{},"duration":10},{"transform":{"skX":-3.58,"skY":-3.58},"duration":5},{"transform":{"skX":-3.58,"skY":-3.58},"duration":5},{"transform":{"skX":-3.58,"skY":-3.58},"duration":1},{"curve":[0.25,0,0.75,1],"transform":{"skX":-3.58,"skY":-3.58},"duration":14},{"transform":{},"duration":0}],"name":"bone10"},{"frame":[{"curve":[0.25,0,1,0],"transform":{},"duration":10},{"transform":{"skX":-39.66,"skY":-39.66},"duration":5},{"curve":[0.25,0,0,1],"transform":{"skX":-39.66,"skY":-39.66},"duration":5},{"transform":{"skX":-5.97,"skY":-5.97},"duration":1},{"curve":[0.25,0,0.75,1],"transform":{"skX":-5.97,"skY":-5.97},"duration":14},{"transform":{},"duration":0}],"name":"bone11"},{"frame":[{"transform":{},"duration":10},{"transform":{},"duration":5},{"transform":{},"duration":5},{"transform":{},"duration":1},{"transform":{},"duration":14},{"transform":{},"duration":0}],"name":"mid2"},{"frame":[{"transform":{},"duration":10},{"transform":{},"duration":5},{"transform":{},"duration":5},{"transform":{},"duration":1},{"transform":{},"duration":14},{"transform":{},"duration":0}],"name":"mid3"},{"frame":[{"transform":{},"duration":10},{"transform":{},"duration":5},{"transform":{},"duration":5},{"transform":{},"duration":1},{"transform":{},"duration":14},{"transform":{},"duration":0}],"name":"mid4"},{"frame":[{"curve":[0.25,0,1,0],"transform":{},"duration":10},{"transform":{"skX":18.42,"skY":18.42},"duration":5},{"transform":{"skX":18.42,"skY":18.42},"duration":5},{"transform":{"skX":18.42,"skY":18.42},"duration":1},{"curve":[0.25,0,0.75,1],"transform":{"skX":18.42,"skY":18.42},"duration":14},{"transform":{},"duration":0}],"name":"bone12"},{"frame":[{"transform":{},"duration":10},{"transform":{},"duration":5},{"curve":[0.25,0,0,1],"transform":{},"duration":5},{"transform":{"skX":10.39,"skY":10.39},"duration":1},{"curve":[0.25,0,0.75,1],"transform":{"skX":10.39,"skY":10.39},"duration":14},{"transform":{},"duration":0}],"name":"mid5"},{"frame":[{"curve":[0.25,0,1,0],"transform":{},"duration":10},{"curve":[0.5309999999999999,0,0.7335,0.415],"transform":{"skX":-51.5,"skY":-51.5},"duration":1},{"curve":[0.107,0.29,0.107,1],"transform":{"y":-2.18,"x":4.6,"skX":-51.5,"skY":-51.5},"duration":1},{"curve":[0.224,0.32,0.517,0.68],"transform":{"y":-2.18,"x":4.6,"skX":-56.29,"skY":-56.29},"duration":1},{"curve":[0.226,0.39,0.54,0.74],"transform":{"y":-2.18,"x":4.6,"skX":-49.12,"skY":-49.12},"duration":1},{"curve":[0.246,0.62,0.569,1],"transform":{"y":-2.18,"x":4.6,"skX":-54.71,"skY":-54.71},"duration":1},{"curve":[0.25,0,0,1],"transform":{"skX":-51.5,"skY":-51.5},"duration":5},{"transform":{"skX":-27.79,"skY":-27.79},"duration":1},{"curve":[0.25,0,0.75,1],"transform":{"skX":-27.79,"skY":-27.79},"duration":14},{"transform":{},"duration":0}],"name":"bone13"},{"frame":[{"transform":{},"duration":10},{"transform":{},"duration":5},{"curve":[0.25,0,0,1],"transform":{},"duration":5},{"transform":{"skX":-19.33,"skY":-19.33},"duration":1},{"curve":[0.25,0,0.75,1],"transform":{"skX":-19.33,"skY":-19.33},"duration":14},{"transform":{},"duration":0}],"name":"bone14"},{"frame":[{"transform":{},"duration":10},{"transform":{},"duration":5},{"transform":{},"duration":5},{"transform":{},"duration":1},{"transform":{},"duration":14},{"transform":{},"duration":0}],"name":"bone15"},{"frame":[{"curve":[0.25,0,1,0],"transform":{},"duration":10},{"transform":{"scX":0.82},"duration":5},{"transform":{"scX":0.82},"duration":5},{"transform":{"scX":0.82},"duration":1},{"curve":[0.25,0,0.75,1],"transform":{"scX":0.82},"duration":14},{"transform":{},"duration":0}],"name":"bone"},{"frame":[{"transform":{},"duration":10},{"transform":{},"duration":5},{"transform":{},"duration":5},{"transform":{},"duration":1},{"transform":{},"duration":14},{"transform":{},"duration":0}],"name":"bone16"},{"frame":[{"tweenEasing":0,"transform":{},"duration":10},{"transform":{},"duration":5},{"transform":{},"duration":20}],"name":"bone19"},{"frame":[{"tweenEasing":0,"transform":{},"duration":10},{"transform":{},"duration":5},{"curve":[0.25,0,0,1],"transform":{},"duration":1},{"curve":[0.25,0,0.75,1],"transform":{"skX":-217.09,"skY":-217.09},"duration":1},{"curve":[0.25,0,0.75,1],"transform":{"skX":-267.79,"skY":-267.79},"duration":3},{"transform":{"skX":-37.45,"skY":-37.45},"duration":1},{"curve":[0.0625,0,0.9375,1],"transform":{"skX":-37.45,"skY":-37.45},"duration":14},{"transform":{"skX":-30.78,"skY":-30.78},"duration":0}],"name":"bone17"},{"frame":[{"tweenEasing":0,"transform":{},"duration":10},{"transform":{},"duration":5},{"transform":{},"duration":5},{"transform":{},"duration":1},{"transform":{},"duration":14}],"name":"bone18"},{"frame":[{"tweenEasing":0,"transform":{},"duration":10},{"transform":{},"duration":5},{"tweenEasing":0,"transform":{},"duration":4},{"transform":{},"duration":16}],"name":"bone20"},{"frame":[{"tweenEasing":0,"transform":{},"duration":16},{"transform":{"y":386.17,"x":157.18,"skX":-45.6,"scY":1.44,"skY":-45.6,"scX":1.18},"duration":19}],"name":"FX"}],"name":"Attack B"},{"ffd":[],"frame":[],"duration":39,"slot":[{"frame":[{"displayIndex":-1,"tweenEasing":0,"duration":39},{"displayIndex":-1,"tweenEasing":null,"duration":0}],"name":"282flip"}],"ik":[],"bone":[{"frame":[{"transform":{},"duration":10},{"transform":{},"duration":5},{"transform":{},"duration":3},{"transform":{},"duration":4},{"transform":{},"duration":17},{"transform":{},"duration":0}],"name":"root"},{"frame":[{"curve":[0.25,0,1,0],"transform":{},"duration":10},{"transform":{"y":19.58,"x":43.18},"duration":5},{"curve":[0.25,0,0,1],"transform":{"y":19.58,"x":43.18},"duration":3},{"transform":{"y":-21.73,"x":-40.2},"duration":4},{"curve":[0.25,0,0.75,1],"transform":{"y":-21.73,"x":-40.2},"duration":17},{"transform":{},"duration":0}],"name":"mid"},{"frame":[{"transform":{},"duration":10},{"transform":{},"duration":5},{"transform":{},"duration":3},{"transform":{},"duration":4},{"transform":{},"duration":17},{"transform":{},"duration":0}],"name":"bone2"},{"frame":[{"transform":{},"duration":10},{"transform":{},"duration":5},{"transform":{},"duration":3},{"transform":{},"duration":4},{"transform":{},"duration":17},{"transform":{},"duration":0}],"name":"bone3"},{"frame":[{"transform":{},"duration":10},{"transform":{},"duration":5},{"transform":{},"duration":3},{"transform":{},"duration":4},{"transform":{},"duration":17},{"transform":{},"duration":0}],"name":"bone4"},{"frame":[{"transform":{},"duration":10},{"transform":{},"duration":5},{"transform":{},"duration":3},{"transform":{},"duration":4},{"transform":{},"duration":17},{"transform":{},"duration":0}],"name":"bone5"},{"frame":[{"curve":[0.25,0,1,0],"transform":{},"duration":10},{"transform":{"skX":-1.22,"skY":-1.22},"duration":5},{"transform":{"skX":-1.22,"skY":-1.22},"duration":3},{"transform":{"skX":-1.22,"skY":-1.22},"duration":4},{"curve":[0.25,0,0.75,1],"transform":{"skX":-1.22,"skY":-1.22},"duration":17},{"transform":{},"duration":0}],"name":"bone6"},{"frame":[{"curve":[0.25,0,1,0],"transform":{},"duration":10},{"transform":{"skX":-30.04,"skY":-30.04},"duration":5},{"curve":[0.25,0,0,1],"transform":{"skX":-30.04,"skY":-30.04},"duration":3},{"transform":{"skX":23.02,"skY":23.02},"duration":4},{"curve":[0.25,0,0.75,1],"transform":{"skX":23.02,"skY":23.02},"duration":17},{"transform":{},"duration":0}],"name":"bone7"},{"frame":[{"curve":[0.25,0,1,0],"transform":{},"duration":10},{"transform":{"skX":63.27,"skY":63.27},"duration":5},{"transform":{"skX":63.27,"skY":63.27},"duration":3},{"transform":{"skX":63.27,"skY":63.27},"duration":4},{"curve":[0.25,0,0.75,1],"transform":{"skX":63.27,"skY":63.27},"duration":17},{"transform":{},"duration":0}],"name":"bone8"},{"frame":[{"curve":[0.25,0,1,0],"transform":{},"duration":10},{"curve":[0.25,0,0.75,1],"transform":{"skX":7.26,"skY":7.26},"duration":1},{"curve":[0.353,0.26,0.618,0.61],"transform":{"y":2.87,"x":0.59,"skX":7.26,"skY":7.26},"duration":1},{"curve":[0.224,0.32,0.517,0.68],"transform":{"y":-4.08,"x":-0.84,"skX":7.26,"skY":7.26},"duration":1},{"curve":[0.226,0.39,0.54,0.74],"transform":{"y":0.28,"x":-6.68,"skX":7.26,"skY":7.26},"duration":1},{"curve":[0.246,0.62,0.569,1],"transform":{"y":-1.72,"x":7.55,"skX":7.26,"skY":7.26},"duration":1},{"curve":[0.25,0,0,1],"transform":{"skX":7.26,"skY":7.26},"duration":3},{"transform":{"skX":49.66,"skY":49.66},"duration":4},{"curve":[0.25,0,0.75,1],"transform":{"skX":49.66,"skY":49.66},"duration":17},{"transform":{},"duration":0}],"name":"bone9"},{"frame":[{"curve":[0.25,0,1,0],"transform":{},"duration":10},{"transform":{"skX":13.49,"skY":13.49},"duration":5},{"transform":{"skX":13.49,"skY":13.49},"duration":3},{"transform":{"skX":13.49,"skY":13.49},"duration":4},{"curve":[0.25,0,0.75,1],"transform":{"skX":13.49,"skY":13.49},"duration":17},{"transform":{},"duration":0}],"name":"bone10"},{"frame":[{"curve":[0.25,0,1,0],"transform":{},"duration":10},{"transform":{"y":-13.46,"x":18.46,"skX":-53.63,"skY":-53.63},"duration":5},{"transform":{"y":-13.46,"x":18.46,"skX":-53.63,"skY":-53.63},"duration":3},{"transform":{"y":-13.46,"x":18.46,"skX":-53.63,"skY":-53.63},"duration":4},{"curve":[0.25,0,0.75,1],"transform":{"y":-13.46,"x":18.46,"skX":-53.63,"skY":-53.63},"duration":17},{"transform":{},"duration":0}],"name":"bone11"},{"frame":[{"transform":{},"duration":10},{"transform":{},"duration":5},{"transform":{},"duration":3},{"transform":{},"duration":4},{"transform":{},"duration":17},{"transform":{},"duration":0}],"name":"mid2"},{"frame":[{"curve":[0.25,0,1,0],"transform":{},"duration":10},{"transform":{"skX":8.23,"skY":8.23},"duration":5},{"transform":{"skX":8.23,"skY":8.23},"duration":3},{"transform":{"skX":8.23,"skY":8.23},"duration":4},{"curve":[0.25,0,0.75,1],"transform":{"skX":8.23,"skY":8.23},"duration":17},{"transform":{},"duration":0}],"name":"mid3"},{"frame":[{"curve":[0.25,0,1,0],"transform":{},"duration":10},{"transform":{"skX":-6.46,"skY":-6.46},"duration":5},{"transform":{"skX":-6.46,"skY":-6.46},"duration":3},{"transform":{"skX":-6.46,"skY":-6.46},"duration":4},{"curve":[0.25,0,0.75,1],"transform":{"skX":-6.46,"skY":-6.46},"duration":17},{"transform":{},"duration":0}],"name":"mid4"},{"frame":[{"transform":{},"duration":10},{"transform":{},"duration":5},{"transform":{},"duration":3},{"transform":{},"duration":4},{"transform":{},"duration":17},{"transform":{},"duration":0}],"name":"bone12"},{"frame":[{"curve":[0.25,0,1,0],"transform":{},"duration":10},{"transform":{"x":15.25,"skX":10.89,"skY":10.89},"duration":5},{"transform":{"x":15.25,"skX":10.89,"skY":10.89},"duration":3},{"transform":{"x":15.25,"skX":10.89,"skY":10.89},"duration":4},{"curve":[0.25,0,0.75,1],"transform":{"x":15.25,"skX":10.89,"skY":10.89},"duration":17},{"transform":{},"duration":0}],"name":"mid5"},{"frame":[{"curve":[0.25,0,1,0],"transform":{},"duration":10},{"transform":{"skX":-18.68,"skY":-18.68},"duration":5},{"curve":[0.25,0,0.75,1],"transform":{"skX":-18.68,"skY":-18.68},"duration":3},{"transform":{},"duration":4},{"transform":{},"duration":17},{"transform":{},"duration":0}],"name":"bone13"},{"frame":[{"curve":[0.25,0,1,0],"transform":{},"duration":10},{"transform":{"skX":35.85,"skY":35.85},"duration":5},{"curve":[0.25,0,0,1],"transform":{"skX":35.85,"skY":35.85},"duration":3},{"transform":{"skX":70.67,"skY":70.67},"duration":4},{"curve":[0.25,0,0.75,1],"transform":{"skX":70.67,"skY":70.67},"duration":17},{"transform":{},"duration":0}],"name":"bone14"},{"frame":[{"transform":{},"duration":10},{"transform":{},"duration":5},{"transform":{},"duration":3},{"transform":{},"duration":4},{"transform":{},"duration":17},{"transform":{},"duration":0}],"name":"bone15"},{"frame":[{"curve":[0.25,0,1,0],"transform":{},"duration":10},{"transform":{"x":39.14,"scX":1.18},"duration":5},{"transform":{"x":39.14,"scX":1.18},"duration":3},{"transform":{"x":39.14,"scX":1.18},"duration":4},{"curve":[0.25,0,0.75,1],"transform":{"x":39.14,"scX":1.18},"duration":17},{"transform":{},"duration":0}],"name":"bone"},{"frame":[{"transform":{},"duration":10},{"transform":{},"duration":5},{"transform":{},"duration":3},{"transform":{},"duration":4},{"transform":{},"duration":17},{"transform":{},"duration":0}],"name":"bone16"},{"frame":[{"tweenEasing":0,"transform":{},"duration":10},{"transform":{},"duration":5},{"transform":{},"duration":3},{"transform":{},"duration":4},{"transform":{},"duration":17}],"name":"bone17"},{"frame":[{"tweenEasing":0,"transform":{},"duration":10},{"transform":{},"duration":5},{"transform":{},"duration":3},{"transform":{},"duration":4},{"transform":{},"duration":17}],"name":"bone18"},{"frame":[{"tweenEasing":0,"transform":{},"duration":10},{"transform":{},"duration":5},{"transform":{},"duration":3},{"transform":{},"duration":4},{"transform":{},"duration":17}],"name":"bone19"},{"frame":[{"tweenEasing":0,"transform":{},"duration":10},{"transform":{},"duration":5},{"transform":{},"duration":3},{"transform":{},"duration":4},{"transform":{},"duration":17}],"name":"bone20"},{"frame":[{"transform":{},"duration":39}],"name":"FX"}],"name":"Attack C"},{"ffd":[],"frame":[],"duration":30,"slot":[{"frame":[{"displayIndex":-1,"tweenEasing":0,"duration":30},{"displayIndex":-1,"tweenEasing":null,"duration":0}],"name":"282flip"}],"ik":[],"bone":[{"frame":[{"transform":{},"duration":10},{"transform":{},"duration":20},{"transform":{},"duration":0}],"name":"root"},{"frame":[{"curve":[0.25,0,0,1],"transform":{},"duration":10},{"curve":[0.25,0,0.75,1],"transform":{"y":23.38,"x":51.19},"duration":20},{"transform":{},"duration":0}],"name":"mid"},{"frame":[{"transform":{},"duration":10},{"transform":{},"duration":20},{"transform":{},"duration":0}],"name":"bone2"},{"frame":[{"transform":{},"duration":10},{"transform":{},"duration":20},{"transform":{},"duration":0}],"name":"bone3"},{"frame":[{"curve":[0.25,0,0,1],"transform":{},"duration":10},{"curve":[0.25,0,0.75,1],"transform":{"skX":-11.66,"skY":-11.66},"duration":20},{"transform":{},"duration":0}],"name":"bone4"},{"frame":[{"transform":{},"duration":10},{"transform":{},"duration":20},{"transform":{},"duration":0}],"name":"bone5"},{"frame":[{"curve":[0.25,0,0,1],"transform":{},"duration":10},{"curve":[0.25,0,0.75,1],"transform":{"skX":-16.88,"skY":-16.88},"duration":20},{"transform":{},"duration":0}],"name":"bone6"},{"frame":[{"transform":{},"duration":10},{"transform":{},"duration":20},{"transform":{},"duration":0}],"name":"bone7"},{"frame":[{"transform":{},"duration":10},{"transform":{},"duration":20},{"transform":{},"duration":0}],"name":"bone8"},{"frame":[{"transform":{},"duration":10},{"transform":{},"duration":20},{"transform":{},"duration":0}],"name":"bone9"},{"frame":[{"curve":[0.25,0,0,1],"transform":{},"duration":10},{"curve":[0.25,0,0.75,1],"transform":{"skX":13.55,"skY":13.55},"duration":20},{"transform":{},"duration":0}],"name":"bone10"},{"frame":[{"curve":[0.25,0,0,1],"transform":{},"duration":10},{"curve":[0.25,0,0.75,1],"transform":{"skX":-30.99,"skY":-30.99},"duration":20},{"transform":{},"duration":0}],"name":"bone11"},{"frame":[{"transform":{},"duration":10},{"transform":{},"duration":20},{"transform":{},"duration":0}],"name":"mid2"},{"frame":[{"curve":[0.25,0,0,1],"transform":{},"duration":10},{"curve":[0.25,0,0.75,1],"transform":{"skX":17.54,"skY":17.54},"duration":20},{"transform":{},"duration":0}],"name":"mid3"},{"frame":[{"curve":[0.25,0,0,1],"transform":{},"duration":10},{"curve":[0.25,0,0.75,1],"transform":{"skX":18.89,"skY":18.89},"duration":20},{"transform":{},"duration":0}],"name":"mid4"},{"frame":[{"curve":[0.25,0,0,1],"transform":{},"duration":10},{"curve":[0.25,0,0.75,1],"transform":{"skX":29.32,"skY":29.32},"duration":20},{"transform":{},"duration":0}],"name":"bone12"},{"frame":[{"curve":[0.25,0,0,1],"transform":{},"duration":10},{"curve":[0.25,0,0.75,1],"transform":{"skX":9.43,"skY":9.43},"duration":20},{"transform":{},"duration":0}],"name":"mid5"},{"frame":[{"curve":[0.25,0,0,1],"transform":{},"duration":10},{"curve":[0.25,0,0.75,1],"transform":{"skX":-25.26,"skY":-25.26},"duration":20},{"transform":{},"duration":0}],"name":"bone13"},{"frame":[{"curve":[0.25,0,0,1],"transform":{},"duration":10},{"curve":[0.25,0,0.75,1],"transform":{"skX":26.97,"skY":26.97},"duration":20},{"transform":{},"duration":0}],"name":"bone14"},{"frame":[{"transform":{},"duration":10},{"transform":{},"duration":20},{"transform":{},"duration":0}],"name":"bone15"},{"frame":[{"curve":[0.25,0,0,1],"transform":{},"duration":10},{"curve":[0.25,0,0.75,1],"transform":{"scX":1.2},"duration":20},{"transform":{},"duration":0}],"name":"bone"},{"frame":[{"transform":{},"duration":10},{"transform":{},"duration":20},{"transform":{},"duration":0}],"name":"bone16"},{"frame":[{"tweenEasing":0,"transform":{},"duration":10},{"transform":{"skX":-38.6,"skY":-38.6},"duration":20}],"name":"bone17"},{"frame":[{"tweenEasing":0,"transform":{},"duration":10},{"transform":{},"duration":20}],"name":"bone18"},{"frame":[{"tweenEasing":0,"transform":{},"duration":10},{"transform":{},"duration":20}],"name":"bone19"},{"frame":[{"tweenEasing":0,"transform":{},"duration":10},{"transform":{},"duration":20}],"name":"bone20"},{"frame":[{"transform":{},"duration":30}],"name":"FX"}],"name":"Damage"},{"ffd":[],"frame":[],"duration":60,"slot":[{"frame":[{"displayIndex":-1,"tweenEasing":null,"duration":60}],"name":"282flip"}],"ik":[],"bone":[{"frame":[{"transform":{},"duration":60},{"transform":{},"duration":0}],"name":"root"},{"frame":[{"curve":[0.25,0,0.75,1],"transform":{},"duration":30},{"curve":[0.25,0,0.75,1],"transform":{"y":26},"duration":30},{"transform":{},"duration":0}],"name":"mid"},{"frame":[{"transform":{},"duration":60},{"transform":{},"duration":0}],"name":"bone2"},{"frame":[{"transform":{},"duration":60},{"transform":{},"duration":0}],"name":"bone3"},{"frame":[{"transform":{},"duration":60},{"transform":{},"duration":0}],"name":"bone4"},{"frame":[{"transform":{},"duration":60},{"transform":{},"duration":0}],"name":"bone5"},{"frame":[{"transform":{},"duration":60},{"transform":{},"duration":0}],"name":"bone6"},{"frame":[{"curve":[0.25,0,0.75,1],"transform":{},"duration":30},{"curve":[0.25,0,0.75,1],"transform":{"skX":-8.67,"skY":-8.67},"duration":30},{"transform":{},"duration":0}],"name":"bone7"},{"frame":[{"transform":{},"duration":60},{"transform":{},"duration":0}],"name":"bone8"},{"frame":[{"curve":[0.25,0,0.75,1],"transform":{},"duration":30},{"curve":[0.25,0,0.75,1],"transform":{"skX":7.81,"skY":7.81},"duration":30},{"transform":{},"duration":0}],"name":"bone9"},{"frame":[{"transform":{},"duration":60},{"transform":{},"duration":0}],"name":"bone10"},{"frame":[{"curve":[0.25,0,0.75,1],"transform":{},"duration":30},{"curve":[0.25,0,0.75,1],"transform":{"skX":-15.82,"skY":-15.82},"duration":30},{"transform":{},"duration":0}],"name":"bone11"},{"frame":[{"transform":{},"duration":60},{"transform":{},"duration":0}],"name":"mid2"},{"frame":[{"curve":[0.25,0,0.75,1],"transform":{},"duration":30},{"curve":[0.25,0,0.75,1],"transform":{"skX":19.14,"skY":19.14},"duration":30},{"transform":{},"duration":0}],"name":"mid3"},{"frame":[{"curve":[0.25,0,0.75,1],"transform":{},"duration":30},{"curve":[0.25,0,0.75,1],"transform":{"skX":-11.1,"skY":-11.1},"duration":30},{"transform":{},"duration":0}],"name":"mid4"},{"frame":[{"curve":[0.25,0,0.75,1],"transform":{},"duration":30},{"curve":[0.25,0,0.75,1],"transform":{"skX":-14.25,"skY":-14.25},"duration":30},{"transform":{},"duration":0}],"name":"bone12"},{"frame":[{"curve":[0.25,0,0.75,1],"transform":{},"duration":30},{"curve":[0.25,0,0.75,1],"transform":{"skX":5.6,"skY":5.6},"duration":30},{"transform":{},"duration":0}],"name":"mid5"},{"frame":[{"curve":[0.25,0,0.75,1],"transform":{},"duration":30},{"curve":[0.25,0,0.75,1],"transform":{"skX":-12.86,"skY":-12.86},"duration":30},{"transform":{},"duration":0}],"name":"bone13"},{"frame":[{"curve":[0.25,0,0.75,1],"transform":{},"duration":30},{"curve":[0.25,0,0.75,1],"transform":{"skX":12.65,"skY":12.65},"duration":30},{"transform":{},"duration":0}],"name":"bone14"},{"frame":[{"curve":[0.25,0,0.75,1],"transform":{},"duration":30},{"curve":[0.25,0,0.75,1],"transform":{"skX":-9.07,"skY":-9.07},"duration":30},{"transform":{},"duration":0}],"name":"bone15"},{"frame":[{"curve":[0.25,0,0.75,1],"transform":{},"duration":30},{"curve":[0.25,0,0.75,1],"transform":{"scX":1.14},"duration":30},{"transform":{},"duration":0}],"name":"bone"},{"frame":[{"curve":[0.25,0,0.75,1],"transform":{},"duration":30},{"curve":[0.25,0,0.75,1],"transform":{"skX":-4.39,"skY":-4.39},"duration":30},{"transform":{},"duration":0}],"name":"bone16"},{"frame":[{"transform":{},"duration":60}],"name":"FX"},{"frame":[{"transform":{},"duration":60}],"name":"bone17"},{"frame":[{"transform":{},"duration":60}],"name":"bone18"},{"frame":[{"transform":{},"duration":60}],"name":"bone19"},{"frame":[{"transform":{},"duration":60}],"name":"bone20"}],"name":"Idle"}],"skin":[{"name":"","slot":[{"display":[{"width":496,"type":"mesh","vertices":[-310.17,-10.53,-20.81,10.65,-9.36,20.4,20.92,23.9,24.68,13.46,83.29,19.69,94.59,12.34,141.28,19.36,148.23,43.31,169.78,61.5,153.11,72.19,144.71,93.78,154.38,113.07,167.57,119.25,191.02,117.08,204.24,96.46,200.14,72.56,204.19,67.56,232.25,63.2,251.92,38.35,254.6,-2.85,279.03,-24.8,270.3,-118.9,247.73,-182.71,202.9,-254.9,129.06,-330.95,39.95,-367.04,7.88,-364.07,90.93,-319.5,151.65,-236.27,176.74,-175.1,180.29,-117.78,176.29,-52.91,154.45,-38.57,144.67,-11.3,120.35,-10.12,90.78,-14.41,21.6,-9.93,5.63,-18.6,-1.51,-12.14,-74.79,-15.89,-152.95,-25.74,-173.67,-23.64,-203.49,-32.47,-217.18,-27.46,-293.79,-36.71,-298.62,-35.73,-311.16,-23.14,106,-325.13,177.52,-244.03,209.11,-182.12,229.05,-117.85,210.72,-50.46,196.29,8.71,187.41,63.78,175.65,92.41],"transform":{},"height":588,"edges":[26,27,27,28,28,29,29,30,30,31,31,32,32,33,33,34,34,35,35,36,36,37,37,38,38,39,39,40,40,41,41,42,42,43,43,44,44,45,45,46,46,47,47,0,0,1,1,2,2,3,3,4,4,5,5,6,6,7,7,8,8,9,9,10,10,11,11,12,12,13,13,14,14,15,15,16,16,17,17,18,18,19,19,20,20,21,21,22,22,23,23,24,24,25,25,26],"path":"Layer 289","userEdges":[27,48,48,49,49,50,50,51,51,52,52,53,53,54,54,55],"uvs":[0.65055,1,0.74691,0.51332,0.76862,0.49546,0.78128,0.44473,0.76102,0.43672,0.78445,0.33846,0.77178,0.31817,0.79457,0.2402,0.84395,0.23219,0.88447,0.19855,0.90283,0.22845,0.94461,0.24608,0.98513,0.23272,1,0.21136,1,0.17131,0.96107,0.14568,0.91232,0.14889,0.90303,0.14124,0.8995,0.09303,0.85328,0.05582,0.77108,0.04481,0.73156,0,0.54103,0,0.40873,0.02821,0.25546,0.09279,0.08905,0.20589,0,0.35113,0,0.40589,0.1141,0.27643,0.28332,0.1825,0.41079,0.14963,0.52651,0.1526,0.656,0.16957,0.68072,0.20881,0.73365,0.22964,0.73149,0.27101,0.71738,0.32042,0.7135,0.43827,0.69311,0.46395,0.70475,0.47705,0.68358,0.60056,0.64928,0.73137,0.64963,0.76679,0.62634,0.81589,0.63385,0.83987,0.60104,0.96815,0.6021,0.97648,0.62503,0.99969,0.1016,0.2482,0.27255,0.13748,0.40272,0.0937,0.53545,0.07002,0.66732,0.11164,0.78342,0.14538,0.89232,0.16906,0.94763,0.19346],"name":"Layer 289","triangles":[42,44,0,55,12,13,55,13,14,15,55,14,55,11,12,10,11,55,16,55,15,9,10,55,54,9,55,16,54,55,17,54,16,18,53,17,53,54,17,19,53,18,53,9,54,53,8,9,53,7,8,20,53,19,37,4,5,36,37,5,33,34,53,20,52,53,35,6,7,34,35,7,53,34,7,44,45,0,4,39,2,4,2,3,6,36,5,32,33,53,52,32,53,43,44,42,37,39,4,21,52,20,35,36,6,39,1,2,39,40,1,38,39,37,22,52,21,22,51,52,46,47,0,45,46,0,31,32,52,51,31,52,50,30,31,50,31,51,23,51,22,23,50,51,24,50,23,50,49,30,49,29,30,24,49,50,48,28,29,24,25,49,25,26,48,40,41,1,41,42,1,42,0,1,28,27,48,26,27,48,29,48,49,25,48,49]}],"name":"Layer 289"},{"display":[{"edges":[13,14,14,15,15,16,16,17,17,18,18,19,19,20,20,21,21,22,22,23,23,0,0,1,1,2,2,3,3,4,4,5,5,6,6,7,7,8,8,9,9,10,10,11,11,12,12,13],"triangles":[22,0,1,7,8,5,8,4,5,7,5,6,21,22,1,20,21,1,8,10,4,10,3,4,10,11,3,11,14,3,19,20,1,9,10,8,17,2,3,2,19,1,22,23,0,15,17,3,14,15,3,17,19,2,15,16,17,13,14,11,12,13,11,17,18,19],"uvs":[0.54287,0.99531,0.59078,0.69939,0.49674,0.57847,0.56239,0.39561,0.82855,0.28059,1,0.06234,0.99712,0.01023,0.9013,0,0.61208,0.12919,0.57481,0.10953,0.51626,0.14394,0.36011,0.13902,0.21106,0.11641,0,0.22652,0.09573,0.36612,0.10283,0.40544,0.10638,0.47426,0.17203,0.52538,0.28027,0.91764,0.37786,0.82818,0.40092,0.85079,0.43109,0.89798,0.46835,0.93042,0.50029,1],"vertices":[264.77,-219.94,190.1,-266.4,151.2,-268.75,107.72,-302.74,96.98,-357.04,51.96,-411.24,37.98,-417.76,28.19,-405.1,40.98,-345.53,33.03,-342.69,37.8,-329.53,24.97,-307.32,7.99,-288.51,21.5,-242.92,65.46,-238.34,76.38,-234.13,94.83,-225.48,113.18,-228.28,224.85,-191.84,208.42,-218.06,216.09,-218.42,230.79,-216.55,242.12,-217.67,262.87,-213.08],"bonePose":[23,0.9646494687623132,0.26353633984061253,-0.26353633984061253,0.9646494687623132,48.32605271564907,-271.9318892919266,21,-0.37751757400260755,0.9260024197156214,-0.9260024197156214,-0.37751757400260755,73.03224494093962,-341.4597618735539,19,0.439468903432369,0.898257804261088,-0.898257804261088,0.439468903432369,39.092061528857755,-410.8322120966377],"path":"282flip","userEdges":[10,4],"name":"282flip","type":"mesh","transform":{},"slotPose":[1,0,0,1,0,0],"width":164,"height":296,"weights":[1,23,1,1,23,1,2,21,0.0041,23,0.9959,3,19,0.00062,21,0.49048,23,0.5089,3,19,0.83188,21,0.16576,23,0.00236,1,19,1,1,19,1,1,19,1,2,19,0.60859,21,0.39141,2,19,0.47226,21,0.52774,2,19,0.23906,21,0.76094,2,19,0.00919,21,0.99081,1,21,1,2,21,0.60096,23,0.39904,2,21,0.00016,23,0.99984,1,23,1,1,23,1,1,23,1,1,23,1,1,23,1,1,23,1,1,23,1,1,23,1,1,23,1]}],"name":"282flip"},{"display":[{"path":"smear","type":"image","name":"smear","transform":{"y":146.87,"x":333.99,"skX":0.25,"skY":0.25}}],"name":"smear"},{"display":[{"path":"Layer 281","type":"image","name":"Layer 281","transform":{"y":-13.61,"x":80.32,"skX":-123.15,"skY":-123.15}}],"name":"Layer 281"},{"display":[{"width":112,"type":"mesh","vertices":[54.46,64.12,38.08,51.36,21.71,38.59,5.33,25.83,-11.05,13.06,-7.44,-5.51,-1.29,-18.18,13.75,-24.05,29.52,-19.86,51.96,-40.77,61.47,-53.81,70.98,-66.84,73.17,-52.05,75.36,-37.25,79.74,-7.67,67.44,3.26,73.51,27.99,72.49,38.72,63.04,53.47,37.31,11.09,11.84,-0.64,55.73,33.89,50.26,-13.15,35.36,30.3,64.97,-19.17,53.89,21.26,24.19,17.35,33.98,-0.85,51.25,0.38,49.17,-23.24],"transform":{},"height":102,"edges":[4,3,3,2,2,1,1,0,0,18,18,17,17,16,16,15,15,14,14,13,13,12,12,11,11,10,10,9,9,8,8,7,7,6,6,5,5,4],"path":"Layer 286","userEdges":[],"uvs":[0.25184,1,0.18888,0.80851,0.12592,0.61703,0.06296,0.42554,0,0.23405,0.11568,0.09889,0.22243,0.02593,0.36403,0.05583,0.46316,0.17305,0.73221,0.11683,0.86611,0.05842,1,0,0.94612,0.13416,0.89225,0.26833,0.7845,0.53666,0.63962,0.56297,0.56773,0.79979,0.50891,0.88352,0.3673,0.95648,0.37469,0.47049,0.23816,0.24004,0.40529,0.75587,0.58788,0.3371,0.26853,0.61954,0.72769,0.36401,0.45152,0.64143,0.24579,0.45383,0.40637,0.35401,0.53103,0.45446,0.62773,0.24774],"name":"Layer 286","triangles":[10,12,11,24,14,13,10,13,12,10,9,13,9,24,13,29,24,9,24,15,14,22,28,15,22,15,24,29,22,24,8,29,9,25,16,15,28,25,15,8,22,29,25,21,16,27,28,22,8,27,22,21,17,16,19,25,28,27,19,28,21,18,17,19,23,25,20,27,8,7,20,8,23,21,25,26,19,27,20,26,27,1,18,21,23,1,21,6,20,7,1,0,18,26,23,19,6,5,20,3,26,20,26,2,23,2,1,23,3,2,26,5,4,20,4,3,20]}],"name":"Layer 286"},{"display":[{"path":"coffin","type":"image","name":"coffin","transform":{"y":11.68,"x":91.56,"skX":27.65,"skY":27.65}}],"name":"coffin"},{"display":[{"path":"Layer 287","type":"image","name":"Layer 287","transform":{"y":4.1,"x":15.79,"skX":123.76,"skY":123.76}}],"name":"Layer 287"},{"display":[{"edges":[0,1,1,2,2,3,3,4,4,5,5,6,6,7,7,8,8,9,9,10,10,11,11,12,12,13,13,14,14,15,15,16,16,17,17,18,18,19,19,20,20,21,21,22,22,23,23,24,24,25,25,26,26,27,27,28,28,29,29,30,30,31,31,0],"triangles":[17,18,19,26,23,24,26,24,25,26,27,23,4,22,23,27,4,23,22,5,21,5,20,21,4,5,22,7,19,20,6,7,20,5,6,20,8,17,19,7,8,19,28,4,27,8,9,17,3,4,28,9,16,17,11,14,15,10,15,16,9,10,16,10,11,15,30,3,28,12,13,14,11,12,14,29,30,28,2,3,30,1,2,30,31,1,30,0,1,31],"uvs":[0,0.03469,0.02663,0.0925,0.11022,0.18575,0.24441,0.29274,0.47329,0.39966,0.49266,0.48682,0.53923,0.56546,0.53866,0.58846,0.47864,0.66864,0.44718,0.75851,0.46064,0.85766,0.46513,0.90553,0.45447,0.96179,0.48588,1,0.52178,0.9335,0.5863,0.86792,0.60313,0.83808,0.62388,0.81415,0.7142,0.92324,0.77983,0.67118,0.81795,0.53463,0.87573,0.4678,0.87292,0.41621,0.89503,0.36214,1,0.25211,1,0.2234,0.77224,0.12642,0.62358,0.14818,0.48278,0.14321,0.42585,0.10898,0.38266,0.13042,0.07902,0],"vertices":[29.15,-407.96,33.51,-390.85,47.21,-363.24,69.22,-331.57,106.75,-299.91,109.94,-274.11,117.56,-250.83,117.48,-244.02,107.63,-220.29,102.46,-193.69,104.67,-164.34,105.41,-150.17,103.66,-133.52,108.81,-122.21,114.7,-141.89,125.28,-161.31,128.04,-170.13,131.44,-177.22,146.25,-144.92,157.03,-219.54,163.28,-259.96,172.76,-279.73,172.3,-295.01,175.93,-311,193.14,-343.58,193.14,-352.07,155.8,-380.78,131.41,-374.35,108.32,-375.82,98.98,-385.96,91.9,-379.61,42.11,-418.23],"bonePose":[13,0.6740445769666508,0.73869067156818,-0.73869067156818,0.6740445769666508,39.685088234686745,-407.7087493825696,22,0.9996753563210984,0.025479049516900495,-0.025479049516900495,0.9996753563210984,91.22253658955684,-351.2284606344666,24,-0.17124132238785783,0.9852291152350592,-0.9852291152350592,-0.17124132238785783,151.78119089703736,-347.2641967094647],"path":"Layer 285","userEdges":[30,3,3,28],"name":"Layer 285","type":"mesh","transform":{},"slotPose":[1,0,0,1,0,0],"width":164,"height":296,"weights":[1,13,1,1,13,1,1,13,1,3,13,0.76162,22,0.21491,24,0.02347,3,13,0.008,22,0.3195,24,0.67249,2,22,0.03852,24,0.96148,2,22,0.00052,24,0.99948,1,24,1,1,24,1,1,24,1,1,24,1,1,24,1,1,24,1,1,24,1,1,24,1,1,24,1,1,24,1,1,24,1,1,24,1,1,24,1,1,24,1,1,24,1,1,24,1,1,24,1,2,22,0.05667,24,0.94333,2,22,0.09441,24,0.90559,2,22,0.99316,24,0.00684,2,13,0.01127,22,0.98873,2,13,0.32751,22,0.67249,2,13,0.60514,22,0.39486,2,13,0.75912,22,0.24088,1,13,1]}],"name":"Layer 285"},{"display":[{"path":"shasdow","type":"image","name":"shasdow","transform":{"y":1.58,"x":12.02}}],"name":"shasdow"},{"display":[{"width":65,"type":"mesh","vertices":[24.12,-36.95,30.79,-34.57,40.46,-27.24,46.45,-11.16,57.21,-6.96,60.73,5.37,64.24,17.7,49.17,11.9,34.11,6.11,22.15,9.13,10.18,12.15,2.05,11.4,-4,0.1,1.07,-6.48,6.14,-13.07,11.21,-19.66,16.28,-26.25,20.97,-3.41,28.12,-16.91,7.08,1.45,35.77,-2.69,49.88,-0.69,17.88,-14.88,35.97,-16.91,29.25,-26.49,12.54,-4.55,27.75,-10.94,42.24,3.66,56.01,8.58],"transform":{},"height":54,"edges":[6,5,5,4,4,3,3,2,2,1,1,0,0,16,16,15,15,14,14,13,13,12,12,11,11,10,10,9,9,8,8,7,7,6],"path":"Layer 283","userEdges":[],"uvs":[1,0.96025,0.89612,1,0.70939,1,0.48656,0.82992,0.31551,0.88847,0.15776,0.74586,0,0.60325,0.23857,0.52014,0.47714,0.43703,0.59562,0.25853,0.71409,0.08003,0.8208,0,1,0.09892,0.99914,0.25286,0.99828,0.40681,0.99741,0.56075,0.99655,0.71469,0.72665,0.43021,0.76452,0.70949,0.85166,0.20319,0.53862,0.58531,0.34698,0.71382,0.87117,0.5649,0.66838,0.79744,0.83974,0.86345,0.84045,0.35274,0.71355,0.61721,0.40029,0.56414,0.18574,0.64573],"name":"Layer 283","triangles":[19,25,13,19,13,12,11,19,12,16,24,0,24,1,0,22,16,15,13,25,14,22,15,14,25,22,14,22,18,16,18,24,16,25,17,22,24,2,1,11,10,19,26,18,22,17,26,22,10,9,19,19,9,25,9,17,25,18,23,24,23,2,24,26,23,18,9,8,17,8,20,17,17,20,26,20,23,26,23,3,2,20,3,23,21,3,20,27,21,20,8,27,20,21,4,3,7,27,8,7,21,27,7,28,21,5,4,21,28,5,21,6,28,7,6,5,28]}],"name":"Layer 283"},{"display":[{"path":"Layer 280","type":"image","name":"Layer 280","transform":{"y":5.25,"x":32.32,"skX":-72,"skY":-72}}],"name":"Layer 280"},{"display":[{"edges":[18,19,19,20,20,21,21,22,22,23,23,24,24,0,0,1,1,2,2,3,3,4,4,5,5,6,6,7,7,8,8,9,9,10,10,11,11,12,12,13,13,14,14,15,15,16,16,17,17,18],"triangles":[1,23,0,11,13,6,9,10,8,10,11,8,8,11,7,11,6,7,23,24,0,12,13,11,14,5,6,13,14,6,14,15,5,3,4,5,15,3,5,3,1,2,15,17,3,22,23,1,17,19,3,20,1,3,19,20,3,21,22,1,20,21,1,16,17,15,18,19,17],"uvs":[0.75394,1,0.56837,0.73246,0.6827,0.69814,0.67607,0.57315,0.71086,0.5441,0.72578,0.44464,0.82022,0.3619,1,0.22458,1,0.05871,0.95743,0,0.69399,0.09744,0.70227,0.13969,0.56972,0.21275,0.56475,0.24619,0.53413,0.25887,0.29468,0.35798,0.15551,0.36766,0.09752,0.41343,0,0.43456,0,0.57099,0.07432,0.70829,0.21515,0.79015,0.30297,0.81656,0.48191,0.92394,0.69399,1],"vertices":[-19.96,-214.23,-38.88,-265.61,-27.22,-272.19,-27.9,-296.19,-24.35,-301.77,-22.83,-320.86,-13.19,-336.75,5.15,-363.11,5.15,-394.96,0.8,-406.24,-29.28,-385.5,-25.23,-379.42,-38.75,-365.39,-39.25,-358.97,-42.37,-356.54,-66.8,-337.51,-81,-335.65,-86.91,-326.86,-96.86,-322.8,-96.85,-296.61,-89.28,-270.25,-74.91,-254.53,-65.95,-249.46,-47.71,-228.84,-26.08,-214.24],"bonePose":[20,-0.7425606159726109,0.6697788676917006,-0.6697788676917006,-0.7425606159726109,-28.6338377100895,-346.31939853240283,14,-0.47807879358819216,0.8783169514026578,-0.8783169514026578,-0.47807879358819216,2.066267894649904,-402.40727258605057],"path":"Layer 282","userEdges":[13,6,6,14],"name":"Layer 282","type":"mesh","transform":{},"slotPose":[1,0,0,1,0,0],"width":102,"height":192,"weights":[1,20,1,1,20,1,1,20,1,1,20,1,1,20,1,1,20,1,2,14,0.36396,20,0.63604,1,14,1,1,14,1,1,14,1,2,14,0.99945,20,0.00055,2,14,0.98732,20,0.01268,2,14,0.62577,20,0.37423,2,14,0.35675,20,0.64325,2,14,0.14197,20,0.85803,1,20,1,1,20,1,1,20,1,1,20,1,1,20,1,1,20,1,1,20,1,1,20,1,1,20,1,1,20,1]}],"name":"Layer 282"},{"display":[{"path":"Group 3 copy","type":"image","name":"Group 3 copy","transform":{"y":1.64,"x":21.87,"skX":-127.61,"skY":-127.61}}],"name":"Group 3 copy"},{"display":[{"edges":[0,48,48,47,47,46,46,45,45,44,44,43,43,42,42,41,41,40,40,39,39,38,38,37,37,36,36,35,35,34,34,33,33,32,32,31,31,30,30,29,29,28,28,27,27,26,26,25,25,24,24,23,23,22,22,21,21,20,20,19,19,18,18,17,17,16,16,15,15,14,14,13,13,12,12,11,11,10,10,9,9,8,8,7,7,6,6,5,5,4,4,3,3,2,2,1,1,0],"triangles":[32,31,33,31,34,33,31,30,34,30,35,34,66,35,30,29,66,30,66,36,35,66,37,36,28,27,29,27,66,29,65,66,27,26,65,27,63,39,66,62,63,66,39,37,66,65,62,66,39,38,37,57,56,16,57,16,15,25,65,26,14,57,15,64,65,25,13,57,14,22,24,23,22,64,24,20,22,21,56,17,16,24,64,25,20,52,22,52,64,22,56,55,17,17,19,18,55,19,17,64,50,65,50,62,65,39,41,40,54,56,57,13,12,57,19,52,20,63,41,39,54,53,56,12,54,57,11,54,12,52,50,64,53,55,56,55,58,19,58,52,19,61,62,50,58,59,52,53,58,55,61,50,52,63,42,41,60,61,52,59,60,52,62,48,63,63,43,42,1,62,61,11,10,54,63,44,43,48,47,63,45,44,63,49,1,61,60,49,61,7,6,58,54,8,53,8,7,53,7,58,53,0,48,62,6,59,58,9,8,54,10,9,54,51,49,60,6,5,59,5,51,59,51,60,59,1,0,62,47,45,63,2,49,51,5,2,51,3,2,5,4,3,5,2,1,49,47,46,45],"uvs":[0,0.63843,0.12342,0.39961,0.12911,0.31488,0.10254,0.2755,0.11868,0.24212,0.16612,0.23784,0.23064,0.19077,0.24867,0.15054,0.22795,0.13141,0.2361,0.08152,0.25936,0.06788,0.28262,0.02487,0.34891,0,0.39886,0,0.45415,0,0.48904,0.05634,0.45008,0.14236,0.41868,0.18379,0.43496,0.21264,0.39252,0.24149,0.40971,0.28526,0.45042,0.29837,0.44227,0.32879,0.45507,0.33876,0.44751,0.37547,0.44635,0.39278,0.49344,0.42111,0.61264,0.44104,0.66323,0.44995,0.66148,0.48952,0.68823,0.52413,0.84988,0.50368,1,0.45123,1,0.48479,0.85295,0.60858,0.68232,0.76902,0.56695,0.87751,0.53787,0.88171,0.52529,0.93119,0.40551,0.92228,0.42644,0.96371,0.35609,0.97158,0.31597,0.99885,0.2648,1,0.22293,1,0.15025,0.94431,0.13571,0.95637,0.06808,0.88189,0.00877,0.72349,0.18269,0.34171,0.32473,0.37447,0.20993,0.26783,0.36948,0.29708,0.28841,0.13951,0.28263,0.09674,0.38159,0.17118,0.4058,0.13012,0.40869,0.05814,0.28195,0.20303,0.24263,0.24841,0.2311,0.27171,0.27445,0.36288,0.24169,0.57328,0.24098,0.87216,0.37429,0.38193,0.4258,0.49657,0.55098,0.61951],"vertices":[-99.86,-199.7,-61.22,-282.56,-59.45,-311.97,-67.77,-325.64,-62.71,-337.21,-47.86,-338.7,-27.67,-355.03,-22.03,-368.99,-28.51,-375.63,-25.95,-392.95,-18.67,-397.68,-11.39,-412.61,9.36,-421.23,25,-421.22,42.3,-421.23,53.22,-401.67,41.02,-371.83,31.19,-357.45,36.28,-347.44,23,-337.42,28.38,-322.24,41.12,-317.69,38.57,-307.13,42.57,-303.68,40.21,-290.94,39.84,-284.94,54.59,-275.11,91.9,-268.19,107.73,-265.1,107.18,-251.37,115.55,-239.36,166.15,-246.45,213.14,-264.64,213.14,-253,167.1,-210.05,113.7,-154.37,77.59,-116.73,68.48,-115.27,64.55,-98.1,27.06,-101.2,33.61,-86.82,11.58,-84.08,-0.97,-74.62,-17,-74.23,-30.1,-74.23,-52.84,-93.56,-57.39,-89.37,-78.56,-115.21,-97.12,-170.18,-42.68,-302.66,1.78,-291.29,-34.16,-328.3,15.79,-318.14,-9.58,-372.82,-11.39,-387.66,19.58,-361.82,27.16,-376.07,28.07,-401.05,-11.61,-350.78,-23.92,-335.03,-27.53,-326.95,-13.95,-295.31,-24.21,-222.3,-24.45,-118.59,17.29,-288.7,33.42,-248.91,72.59,-206.26],"bonePose":[10,-0.2895330086184791,0.9571680296167084,-0.9571680296167084,-0.2895330086184791,-32.05182658973442,-287.266427954799,4,0.5602053463545429,-0.8283537709914688,0.8283537709914688,0.5602053463545429,-26.14,-320,8,0.4780787935881922,-0.8783169514026578,0.8783169514026578,0.4780787935881922,-6.258312257877272,-349.39827533248723,11,0.20141984515618444,-0.9795050004860918,0.9795050004860918,0.20141984515618444,4.106435987114736,-368.44018683889686,9,0.7926090059959996,0.6097302383956643,-0.6097302383956643,0.7926090059959996,3.4790438701725144,-284.4085013704877,6,0.05704128853989235,0.99837182021615,-0.99837182021615,0.05704128853989235,-18.41,-296.74],"path":"Layer 284","userEdges":[2,49,5,51,52,20,7,53,53,54,17,55,55,53,55,56,56,57,57,13,53,58,58,59,51,60,60,52,59,60,49,61,61,50,61,62,62,63,63,43,25,64,64,50,52,64,64,65,65,66,66,35],"name":"Layer 284","type":"mesh","transform":{},"slotPose":[1,0,0,1,0,0],"width":313,"height":347,"weights":[1,10,1,2,10,0.91481,4,0.08519,2,10,0.37465,4,0.62535,2,10,0.20247,4,0.79753,2,10,0.16229,4,0.83771,3,10,0.09132,4,0.9085,8,0.00017,3,4,0.7421,8,0.22865,11,0.02925,3,4,0.1606,8,0.49242,11,0.34698,3,4,0.04451,8,0.3823,11,0.57319,3,4,0.00081,8,0.19371,11,0.80548,2,8,0.10677,11,0.89323,2,8,0.00864,11,0.99136,1,11,1,1,11,1,1,11,1,2,8,0.0004,11,0.9996,3,9,0.00267,8,0.16108,11,0.83626,5,6,0.00007,9,0.03411,4,0.03043,8,0.53975,11,0.39564,5,6,0.00087,9,0.06611,4,0.07434,8,0.65534,11,0.20334,5,6,0.01525,9,0.18782,4,0.23961,8,0.51245,11,0.04486,5,6,0.02563,9,0.53718,4,0.25133,8,0.18538,11,0.00048,4,6,0.00659,9,0.69213,4,0.18475,8,0.11652,4,6,0.0031,9,0.76485,4,0.14576,8,0.08629,4,6,0.00037,9,0.80653,4,0.12232,8,0.07078,3,9,0.89935,4,0.06458,8,0.03607,3,9,0.95096,4,0.03141,8,0.01763,3,9,0.99773,4,0.00133,8,0.00094,1,9,1,1,9,1,1,9,1,1,9,1,1,9,1,1,9,1,1,9,1,1,9,1,2,6,0.17878,9,0.82122,2,6,0.59371,9,0.40629,2,6,0.66655,9,0.33345,2,6,0.74802,9,0.25198,2,6,0.92821,9,0.07179,2,6,0.96687,9,0.03313,2,6,0.98732,9,0.01268,3,10,0.00344,6,0.99556,9,0.001,2,10,0.03258,6,0.96742,2,10,0.07568,6,0.92432,2,10,0.35725,6,0.64275,2,10,0.40068,6,0.59932,2,10,0.74627,6,0.25373,1,10,1,3,10,0.54888,6,0.04929,4,0.40183,4,6,0.19619,9,0.76411,4,0.03326,8,0.00645,2,10,0.03778,4,0.96222,4,6,0.06816,9,0.46398,4,0.3124,8,0.15546,3,4,0.03163,8,0.47016,11,0.49821,3,4,0.00091,8,0.13867,11,0.86041,4,9,0.01843,4,0.01194,8,0.54864,11,0.42098,3,9,0.00234,8,0.14211,11,0.85555,1,11,1,3,4,0.69384,8,0.30009,11,0.00607,2,4,0.99561,8,0.00439,2,10,0.00596,4,0.99404,4,6,0.89823,9,0.09195,4,0.00895,8,0.00087,2,10,0.21665,6,0.78335,2,10,0.11457,6,0.88543,4,6,0.004,9,0.93597,4,0.04239,8,0.01764,2,6,0.10081,9,0.89919,2,6,0.10863,9,0.89137]}],"name":"Layer 284"},{"display":[{"path":"Layer 288","type":"image","name":"Layer 288","transform":{"y":-0.67,"x":18.03,"skX":-78.06,"skY":-78.06}}],"name":"Layer 288"}]}],"type":"Armature","frameRate":30,"slot":[{"name":"shasdow","parent":"bone","color":{}},{"z":1,"name":"coffin","parent":"mid5","color":{}},{"z":2,"name":"Layer 280","parent":"bone16","color":{}},{"z":3,"name":"Layer 281","parent":"bone11","color":{}},{"z":4,"name":"Layer 282","parent":"root","color":{}},{"z":5,"name":"Layer 283","parent":"bone14","color":{}},{"z":6,"name":"Layer 284","parent":"root","color":{}},{"z":7,"name":"Layer 285","parent":"root","color":{}},{"z":8,"name":"Layer 286","parent":"bone13","color":{}},{"z":9,"name":"Group 3 copy","parent":"bone15","color":{}},{"z":10,"name":"Layer 287","parent":"bone5","color":{}},{"z":11,"name":"Layer 288","parent":"bone12","color":{}},{"z":12,"name":"Layer 289","parent":"bone8","color":{}},{"z":13,"name":"282flip","parent":"root","color":{}},{"z":14,"displayIndex":-1,"name":"smear","parent":"FX","color":{}}],"aabb":{"width":591.7849793322791,"y":-644.0785746871708,"height":641.7185746871708,"x":-185.8600862453075},"ik":[],"defaultActions":[{"gotoAndPlay":"Attack A"}],"bone":[{"name":"root","transform":{}},{"transform":{"y":-319.72,"x":-26.14},"name":"mid","parent":"root"},{"transform":{"y":-23.44,"x":2.12},"name":"bone","parent":"root"},{"transform":{"y":-433.87,"x":-189.38,"skX":-84.7,"skY":-84.7},"name":"FX","parent":"root"},{"length":35,"transform":{"y":-0.28,"skX":-55.93,"skY":-55.93},"parent":"mid","name":"bone2"},{"length":244,"transform":{"y":50.13,"x":-56.75,"skX":-27.65,"skY":-27.65},"parent":"mid","name":"mid5"},{"length":192,"transform":{"y":22.98,"x":7.73,"skX":86.73,"skY":86.73},"parent":"mid","name":"mid2"},{"length":36,"transform":{"y":59.09,"x":7.04,"skX":134,"skY":134},"parent":"bone2","name":"bone12"},{"length":21,"transform":{"x":35.49,"skX":-5.51,"skY":-5.51},"parent":"bone2","name":"bone3"},{"length":130,"transform":{"y":-21.15,"x":13.56,"skX":-49.16,"skY":-49.16},"parent":"mid2","name":"mid4"},{"length":145,"transform":{"y":14.16,"x":8.68,"skX":20.1,"skY":20.1},"parent":"mid2","name":"mid3"},{"length":41,"transform":{"x":21.68,"skX":-16.94,"skY":-16.94},"parent":"bone3","name":"bone4"},{"length":65,"transform":{"x":41.73,"skX":-45.37,"skY":-45.37},"parent":"bone4","name":"bone5"},{"length":76,"transform":{"y":26.94,"x":45.63,"skX":126,"skY":126},"parent":"bone4","name":"bone6"},{"length":63,"transform":{"y":-8.84,"x":32.86,"skX":-163.06,"skY":-163.06},"parent":"bone4","name":"bone9"},{"length":63,"transform":{"y":17.11,"x":52.6,"skX":110.61,"skY":110.61},"parent":"bone4","name":"bone13"},{"length":52,"transform":{"y":-19.83,"x":26.5,"skX":-138.81,"skY":-138.81},"parent":"bone4","name":"bone14"},{"length":54,"transform":{"y":-0.25,"x":39.37,"skX":-154.01,"skY":-154.01},"parent":"bone4","name":"bone15"},{"length":68,"transform":{"y":2.66,"x":36.94,"skX":150.39,"skY":150.39},"parent":"bone4","name":"bone16"},{"length":77,"transform":{"y":25.73,"x":48.57,"skX":142.31,"skY":142.31},"parent":"bone4","name":"bone17"},{"length":72,"transform":{"y":0.15,"x":63.94,"skX":19.39,"skY":19.39},"parent":"bone9","name":"bone10"},{"length":73,"transform":{"x":77.23,"skX":48.25,"skY":48.25},"parent":"bone17","name":"bone18"},{"length":59,"transform":{"x":76.46,"skX":-46.16,"skY":-46.16},"parent":"bone6","name":"bone7"},{"length":177,"transform":{"y":-3.37,"x":73.71,"skX":-96.9,"skY":-96.9},"parent":"bone18","name":"bone19"},{"length":203,"transform":{"y":2.42,"x":60.64,"skX":98.4,"skY":98.4},"parent":"bone7","name":"bone20"},{"length":114,"transform":{"y":-0.55,"x":66.71,"skX":-86.15,"skY":-86.15},"parent":"bone7","name":"bone8"},{"length":44,"transform":{"x":72.99,"skX":-14.8,"skY":-14.8},"parent":"bone10","name":"bone11"}],"name":"Harbinger"}],"name":"Harbinger","version":"5.0","isGlobal":0}